authWA.py
authwa-0.5.0.dist-info/METADATA
authwa-0.5.0.dist-info/WHEEL
authwa-0.5.0.dist-info/RECORD
